cBinder/BindingsGenerator.py
cBinder/CType.py
cBinder/DoxygenParser.py
cBinder/Enum.py
cBinder/Function.py
cBinder/FunctionParameterTraits.py
cBinder/HeaderFile.py
cBinder/LibPaths.py
cBinder/LibraryFile.py
cBinder/MiniPreprocessing.py
cBinder/PythonWriter.py
cBinder/Scrapers.py
cBinder/SourceFile.py
cBinder/Struct.py
cBinder/WheelGenerator.py
cBinder/WrapperArgumentsProcessing.py
cBinder/WrapperBuilder.py
cBinder/__init__.py
cBinder/__main__.py
cBinder/main.py
cBinder/setup.config
cBinder-1.0.dist-info/LICENSE
cBinder-1.0.dist-info/METADATA
cBinder-1.0.dist-info/WHEEL
cBinder-1.0.dist-info/top_level.txt
cBinder-1.0.dist-info/RECORD
